.gitignore
example.py
setup.py
ebs/__init__.py
ebs/linuxnode/__init__.py
ebs/linuxnode/core/__init__.py
ebs/linuxnode/core/background.py
ebs/linuxnode/core/basemixin.py
ebs/linuxnode/core/basenode.py
ebs/linuxnode/core/busy.py
ebs/linuxnode/core/config.py
ebs/linuxnode/core/constants.py
ebs/linuxnode/core/http.py
ebs/linuxnode/core/log.py
ebs/linuxnode/core/nodeid.py
ebs/linuxnode/core/resources.py
ebs/linuxnode/core/shell.py
ebs/linuxnode/core/tempfs.py
ebs/linuxnode/db/__init__.py
ebs/linuxnode/db/sequence.py
ebs_linuxnode_core.egg-info/PKG-INFO
ebs_linuxnode_core.egg-info/SOURCES.txt
ebs_linuxnode_core.egg-info/dependency_links.txt
ebs_linuxnode_core.egg-info/requires.txt
ebs_linuxnode_core.egg-info/top_level.txt