Metadata-Version: 2.1
Name: ebs-linuxnode-core
Version: 3.2.2
Summary: Twisted based linux application node core
Home-page: https://github.com/ebs-universe/ebs-linuxnode-core
Author: Chintalagiri Shashank
Author-email: shashank.chintalagiri@gmail.com
Classifier: Development Status :: 5 - Production/Stable
Classifier: Intended Audience :: Developers
Classifier: License :: OSI Approved :: GNU General Public License v3 or later (GPLv3+)
Classifier: Programming Language :: Python
Classifier: Programming Language :: Python :: 3
Classifier: Programming Language :: Python :: 3.6
Classifier: Operating System :: POSIX :: Linux
Requires-Dist: six
Requires-Dist: setuptools-scm
Requires-Dist: appdirs
Requires-Dist: twisted[tls]
Requires-Dist: SQLAlchemy
Requires-Dist: arrow
Requires-Dist: raspi_system
Requires-Dist: netifaces
Requires-Dist: ifcfg
Requires-Dist: psutil
Requires-Dist: memory_tempfile
Requires-Dist: treq
